odoo/addons/fieldservice_equipment_stock/README.rst
odoo/addons/fieldservice_equipment_stock/__init__.py
odoo/addons/fieldservice_equipment_stock/__manifest__.py
odoo/addons/fieldservice_equipment_stock/i18n/es.po
odoo/addons/fieldservice_equipment_stock/i18n/es_AR.po
odoo/addons/fieldservice_equipment_stock/i18n/fieldservice_equipment_stock.pot
odoo/addons/fieldservice_equipment_stock/i18n/it.po
odoo/addons/fieldservice_equipment_stock/i18n/pt_BR.po
odoo/addons/fieldservice_equipment_stock/models/__init__.py
odoo/addons/fieldservice_equipment_stock/models/fsm_equipment.py
odoo/addons/fieldservice_equipment_stock/models/product_template.py
odoo/addons/fieldservice_equipment_stock/models/stock_lot.py
odoo/addons/fieldservice_equipment_stock/models/stock_move.py
odoo/addons/fieldservice_equipment_stock/models/stock_picking_type.py
odoo/addons/fieldservice_equipment_stock/readme/CONFIGURE.md
odoo/addons/fieldservice_equipment_stock/readme/CONTRIBUTORS.md
odoo/addons/fieldservice_equipment_stock/readme/CREDITS.md
odoo/addons/fieldservice_equipment_stock/readme/DESCRIPTION.md
odoo/addons/fieldservice_equipment_stock/readme/ROADMAP.md
odoo/addons/fieldservice_equipment_stock/readme/USAGE.md
odoo/addons/fieldservice_equipment_stock/security/ir.model.access.csv
odoo/addons/fieldservice_equipment_stock/static/description/icon.png
odoo/addons/fieldservice_equipment_stock/static/description/index.html
odoo/addons/fieldservice_equipment_stock/tests/__init__.py
odoo/addons/fieldservice_equipment_stock/tests/test_fsm_equipment.py
odoo/addons/fieldservice_equipment_stock/tests/test_stock_move.py
odoo/addons/fieldservice_equipment_stock/views/fsm_equipment.xml
odoo/addons/fieldservice_equipment_stock/views/product_template.xml
odoo/addons/fieldservice_equipment_stock/views/stock_lot.xml
odoo/addons/fieldservice_equipment_stock/views/stock_picking_type.xml
odoo_addon_fieldservice_equipment_stock-18.0.1.0.1.2.dist-info/METADATA
odoo_addon_fieldservice_equipment_stock-18.0.1.0.1.2.dist-info/WHEEL
odoo_addon_fieldservice_equipment_stock-18.0.1.0.1.2.dist-info/top_level.txt
odoo_addon_fieldservice_equipment_stock-18.0.1.0.1.2.dist-info/RECORD
